{
  "result": {
    "verdict": {
      "inputGranularity": "PREMISE",
      "validationGranularity": "PREMISE",
      "geocodeGranularity": "PREMISE",
      "addressComplete": true,
      "hasInferredComponents": true,
      "possibleNextAction": "ACCEPT"
    },
    "address": {
      "formattedAddress": "1600 Amphitheatre Parkway, Mountain View, CA 94043-1351, USA",
      "postalAddress": {
        "regionCode": "US",
        "languageCode": "en",
        "postalCode": "94043-1351",
        "administrativeArea": "CA",
        "locality": "Mountain View",
        "addressLines": [
          "1600 Amphitheatre Pkwy"
        ]
      },
      "addressComponents": [
        {
          "componentName": {
            "text": "1600"
          },
          "componentType": "street_number",
          "confirmationLevel": "CONFIRMED"
        },
        {
          "componentName": {
            "text": "Amphitheatre Parkway",
            "languageCode": "en"
          },
          "componentType": "route",
          "confirmationLevel": "CONFIRMED"
        },
        {
          "componentName": {
            "text": "Mountain View",
            "languageCode": "en"
          },
          "componentType": "locality",
          "confirmationLevel": "CONFIRMED"
        },
        {
          "componentName": {
            "text": "USA",
            "languageCode": "en"
          },
          "componentType": "country",
          "confirmationLevel": "CONFIRMED"
        },
        {
          "componentName": {
            "text": "94043"
          },
          "componentType": "postal_code",
          "confirmationLevel": "CONFIRMED",
          "inferred": true
        },
        {
          "componentName": {
            "text": "CA",
            "languageCode": "en"
          },
          "componentType": "administrative_area_level_1",
          "confirmationLevel": "CONFIRMED",
          "inferred": true
        },
        {
          "componentName": {
            "text": "1351"
          },
          "componentType": "postal_code_suffix",
          "confirmationLevel": "CONFIRMED",
          "inferred": true
        }
      ]
    },
    "geocode": {
      "location": {
        "latitude": 37.4220094,
        "longitude": -122.0847515
      },
      "plusCode": {
        "globalCode": "849VCWC8+R3"
      },
      "bounds": {
        "low": {
          "latitude": 37.4220094,
          "longitude": -122.0847515
        },
        "high": {
          "latitude": 37.4220094,
          "longitude": -122.0847515
        }
      },
      "placeId": "ChIJ09H2YwK6j4ARoF7qfCBxhB8",
      "placeTypes": [
        "street_address"
      ]
    },
    "metadata": {
      "business": true,
      "residential": false
    },
    "uspsData": {
      "standardizedAddress": {
        "firstAddressLine": "1600 AMPHITHEATRE PKWY",
        "cityStateZipAddressLine": "MOUNTAIN VIEW CA 94043-1351",
        "city": "MOUNTAIN VIEW",
        "state": "CA",
        "zipCode": "94043",
        "zipCodeExtension": "1351"
      },
      "deliveryPointCode": "00",
      "deliveryPointCheckDigit": "0",
      "dpvConfirmation": "Y",
      "dpvFootnote": "AABB",
      "dpvCmra": "N",
      "dpvVacant": "N",
      "dpvNoStat": "Y",
      "carrierRoute": "C909",
      "carrierRouteIndicator": "D",
      "postOfficeCity": "MOUNTAIN VIEW",
      "postOfficeState": "CA",
      "fipsCountyCode": "085",
      "county": "SANTA CLARA",
      "elotNumber": "0103",
      "elotFlag": "A",
      "addressRecordType": "S",
      "dpvNoStatReasonCode": 5,
      "dpvDrop": "N",
      "dpvThrowback": "N",
      "dpvNonDeliveryDays": "N",
      "dpvNoSecureLocation": "N",
      "dpvPbsa": "N",
      "dpvDoorNotAccessible": "N",
      "dpvEnhancedDeliveryCode": "Y"
    }
  },
  "responseId": "7fc9bbcb-80dc-41db-ad9c-c182c7eb5b00"
}
